Metadata-Version: 2.1
Name: pylemon8
Version: 0.1.1
Summary: Lemon8 Wrapper in Python
Home-page: https://github.com/shotnothing/pylemon8
Download-URL: https://github.com/shotnothing/pylemon8
Author: Saw Jing Wen
Author-email: shotnothinggg@gmail.com
License: MIT
Keywords: python,lemon8,pylemon8,bytedance,api,lemon,8,wrapper,py-lemon8,pythonlemon8,eight
Classifier: Programming Language :: Python :: 3
Classifier: License :: OSI Approved :: MIT License
Classifier: Operating System :: OS Independent
Classifier: Intended Audience :: Developers
Classifier: Topic :: Software Development :: Build Tools
License-File: LICENSE
